findu/__init__.py
findu/__main__.py
findu/findu.py
findu/findu2.py
findu/notify.py
findu/resources/data.json
findu/result.py
findu/sites.py
findu/tests/__init__.py
findu/tests/all.py
findu/tests/base.py
findu/tests/test_multiple_usernames.py
findu/translations/en_US/LC_MESSAGES/messages.po
findu/translations/fr_FR/LC_MESSAGES/messages.po
findu/translations/zh_CN/LC_MESSAGES/messages.po
findu-0.1.0.dist-info/entry_points.txt
findu-0.1.0.dist-info/LICENSE
findu-0.1.0.dist-info/METADATA
findu-0.1.0.dist-info/WHEEL
findu-0.1.0.dist-info/RECORD
