Metadata-Version: 2.1
Name: findu
Version: 0.1.0
Summary: An interesting python package
Home-page: https://github.com/MarkHoo/findu
License: Apache-2.0
Author: Mark Hoo
Author-email: markhoo@foxmail.com
Requires-Python: >=3.7,<4.0
Classifier: Intended Audience :: Developers
Classifier: Intended Audience :: Information Technology
Classifier: License :: OSI Approved :: Apache Software License
Classifier: Operating System :: MacOS
Classifier: Operating System :: Microsoft :: Windows
Classifier: Operating System :: POSIX
Classifier: Operating System :: Unix
Classifier: Programming Language :: Python :: 3
Classifier: Programming Language :: Python :: 3.7
Classifier: Programming Language :: Python :: 3.8
Classifier: Programming Language :: Python :: 3.9
Classifier: Programming Language :: Python :: 3.10
Classifier: Programming Language :: Python :: 3.11
Classifier: Programming Language :: Python :: 3 :: Only
Classifier: Programming Language :: Python :: 3.12
Classifier: Programming Language :: Python :: Implementation :: CPython
Requires-Dist: PySocks (>=1.7.0,<2.0.0)
Requires-Dist: certifi (>=2022.12.7,<2023.0.0)
Requires-Dist: click (>=8.1.3,<9.0.0)
Requires-Dist: colorama (>=0.4.1,<0.5.0)
Requires-Dist: exrex (>=0.11.0,<0.12.0)
Requires-Dist: openpyxl (>=3.0.10,<4.0.0)
Requires-Dist: pandas (>=2.0.0,<3.0.0)
Requires-Dist: requests (>=2.30.0,<3.0.0)
Requires-Dist: requests-futures (>=1.0.0,<2.0.0)
Requires-Dist: stem (>=1.8.0,<2.0.0)
Requires-Dist: torrequest (>=0.1.0,<0.2.0)
Project-URL: Bug Tracker, https://github.com/MarkHoo/findu/issues
Project-URL: Repository, https://github.com/MarkHoo/findu
